croparray/__init__.py
croparray/crop_array_tools.py
croparray/rSNAPsim_IP.py
croparray-0.1.2.dist-info/LICENSE
croparray-0.1.2.dist-info/METADATA
croparray-0.1.2.dist-info/WHEEL
croparray-0.1.2.dist-info/top_level.txt
croparray-0.1.2.dist-info/RECORD
