Metadata-Version: 2.1
Name: croparray
Version: 0.1.2
Summary: Python module for for creating and manipulating an array of crops (or regions of interest) from images obtained using single-molecule microscopy.
Home-page: https://github.com/Colorado-State-University-Stasevich-Lab/croparray
Author: Tim Stasevich
Author-email: Tim.Stasevich@colostate.edu
License: BSD 3-Clause License
Keywords: Single-molecule image processing
Platform: UNKNOWN
Classifier: Development Status :: 2 - Pre-Alpha
Classifier: Topic :: Scientific/Engineering :: Bio-Informatics
Classifier: Topic :: Scientific/Engineering :: Image Processing
Classifier: License :: OSI Approved :: MIT License
Classifier: Programming Language :: Python :: 3.8
Requires-Python: >=3.7
Requires-Dist: xarray (~=0.18.2)
Requires-Dist: trackpy (~=0.5.0)
Requires-Dist: tifffile (~=2021.11.2)
Requires-Dist: seaborn (~=0.11.2)
Requires-Dist: urllib3 (~=1.24.3)
Requires-Dist: matplotlib (~=3.2.2)
Requires-Dist: imageio (~=2.4.1)
